{
  "seller": [
    {
      "id": "b8b1",
      "name": "",
      "email": "",
      "password": "",
      "confirmPassword": ""
    },
    {
      "id": "ce16",
      "name": null,
      "email": null,
      "password": null,
      "confirmPassword": null
    },
    {
      "id": "4387",
      "name": "jhasdgjhasd",
      "email": "hsdajh",
      "password": "shdhga",
      "confirmPassword": "asdasda"
    },
    {
      "id": "447b",
      "name": "sadasd",
      "email": "dsadasd",
      "password": "dsadasd",
      "confirmPassword": "dasdasdas"
    },
    {
      "id": "af0b",
      "name": "",
      "email": "",
      "password": "",
      "confirmPassword": ""
    }
  ]
}